.bzrignore
COPYING
ChangeLog
INSTALL.txt
Makefile
README.txt
TODO.txt
forms.wpr
jscalendar-1.0.zip
setup.cfg
setup.py
docs/Makefile
docs/index.txt
docs/install.txt
docs/modules.txt
docs/overview.txt
docs/templates.txt
softwarefabrica/__init__.py
softwarefabrica.django.forms.egg-info/PKG-INFO
softwarefabrica.django.forms.egg-info/SOURCES.txt
softwarefabrica.django.forms.egg-info/dependency_links.txt
softwarefabrica.django.forms.egg-info/namespace_packages.txt
softwarefabrica.django.forms.egg-info/not-zip-safe
softwarefabrica.django.forms.egg-info/requires.txt
softwarefabrica.django.forms.egg-info/top_level.txt
softwarefabrica/django/__init__.py
softwarefabrica/django/forms/__init__.py
softwarefabrica/django/forms/bzrcachedrev.py
softwarefabrica/django/forms/extended.py
softwarefabrica/django/forms/fields.py
softwarefabrica/django/forms/finddata.py
softwarefabrica/django/forms/models.py
softwarefabrica/django/forms/urls.py
softwarefabrica/django/forms/version.py
softwarefabrica/django/forms/views.py
softwarefabrica/django/forms/widgets.py
softwarefabrica/django/forms/images/12-em-plus.png
softwarefabrica/django/forms/images/blue_view.gif
softwarefabrica/django/forms/images/icon_addlink.gif
softwarefabrica/django/forms/images/icon_changelink.gif
softwarefabrica/django/forms/images/icon_deletelink.gif
softwarefabrica/django/forms/images/icon_searchbox.png
softwarefabrica/django/forms/images/page.gif
softwarefabrica/django/forms/locale/it/LC_MESSAGES/django.mo
softwarefabrica/django/forms/locale/it/LC_MESSAGES/django.po
softwarefabrica/django/forms/templates/forms/field.html
softwarefabrica/django/forms/templates/forms/form.html
softwarefabrica/django/forms/templates/forms/hiddenfield.html
softwarefabrica/django/forms/templates/forms/js/Related.js
softwarefabrica/django/forms/templates/forms/widgets/date.html
softwarefabrica/django/forms/templates/forms/widgets/datetime.html
softwarefabrica/django/forms/templates/forms/widgets/relateditem.html
softwarefabrica/django/forms/templates/forms/widgets/select-cascade-popup.html
softwarefabrica/django/forms/templates/forms/widgets/select-cascade.html
softwarefabrica/django/forms/templates/forms/widgets/select-popup.html
softwarefabrica/django/forms/tests/__init__.py
softwarefabrica/django/forms/tests/models.py
softwarefabrica/django/forms/tests/settings.py
