Metadata-Version: 1.0
Name: softwarefabrica.django.forms
Version: 0.9dev-BZR-r41-panta-elasticworld.org-20100224160218-ekf7vb0w9fx9318y
Summary: Extended forms library for django
Home-page: http://pypi.python.org/pypi/softwarefabrica.django.forms/
Author: Marco Pantaleoni
Author-email: m.pantaleoni@softwarefabrica.org
License: GNU GPL v2
Download-URL: http://pypi.python.org/packages/source/s/softwarefabrica.django.forms/softwarefabrica.django.forms-0.9dev-BZR-r41-panta-elasticworld.org-20100224160218-ekf7vb0w9fx9318y.tar.gz
Keywords: django forms table softwarefabrica
Platform: UNKNOWN
Classifier: Development Status :: 4 - Beta
Classifier: Framework :: Django
Classifier: Intended Audience :: Developers
Classifier: License :: OSI Approved :: GNU General Public License (GPL)
Classifier: Operating System :: OS Independent
Classifier: Programming Language :: Python :: 2.3
Classifier: Topic :: Software Development :: Libraries :: Python Modules
